[ {
  "openYear" : 2006,
  "openSemester" : 2,
  "openDept" : "실용외국어(필수)(서울)",
  "openCampus" : "Seoul",
  "area" : "실용외국어(필수)",
  "suggestedYear" : 1,
  "courseNumber" : "U71101201",
  "subjectName" : "실용영어1 (Practical English 1)",
  "professorNameMain" : "허윤숙",
  "professorNameAdditional" : "Her Yun Suk",
  "creditHour" : 2,
  "classHour" : 3,
  "time" : [ {
    "dow" : "Mon",
    "time" : [ 1, 2, 3 ],
    "room" : "2204"
  }, {
    "dow" : "Tue",
    "time" : [ 1, 2, 3 ],
    "room" : "2204"
  }, {
    "dow" : "Wed",
    "time" : [ 1, 2, 3 ],
    "room" : "2204"
  }, {
    "dow" : "Thu",
    "time" : [ 1, 2, 3 ],
    "room" : "2204"
  }, {
    "dow" : "Fri",
    "time" : [ 1, 2, 3 ],
    "room" : "2204"
  }, {
    "dow" : "Sat",
    "time" : [ 1, 2, 3 ],
    "room" : "2204"
  } ],
  "applyNo" : 0,
  "maxNo" : 27,
  "note" : "",
  "required" : false,
  "online" : false,
  "foreignLanguage" : false,
  "teamTeaching" : false
}, {
  "openYear" : 2006,
  "openSemester" : 2,
  "openDept" : "실용외국어(필수)(서울)",
  "openCampus" : "Seoul",
  "area" : "실용외국어(필수)",
  "suggestedYear" : 1,
  "courseNumber" : "U71101202",
  "subjectName" : "실용영어1 (Practical English 1)",
  "professorNameMain" : "천정식",
  "professorNameAdditional" : "Chun, JungSik",
  "creditHour" : 2,
  "classHour" : 3,
  "time" : [ {
    "dow" : "Mon",
    "time" : [ 1, 2, 3 ],
    "room" : "2405"
  }, {
    "dow" : "Tue",
    "time" : [ 1, 2, 3 ],
    "room" : "2405"
  }, {
    "dow" : "Wed",
    "time" : [ 1, 2, 3 ],
    "room" : "2405"
  }, {
    "dow" : "Thu",
    "time" : [ 1, 2, 3 ],
    "room" : "2405"
  }, {
    "dow" : "Fri",
    "time" : [ 1, 2, 3 ],
    "room" : "2405"
  }, {
    "dow" : "Sat",
    "time" : [ 1, 2, 3 ],
    "room" : "2405"
  } ],
  "applyNo" : 0,
  "maxNo" : 27,
  "note" : "강변",
  "required" : false,
  "online" : false,
  "foreignLanguage" : false,
  "teamTeaching" : false
}, {
  "openYear" : 2006,
  "openSemester" : 2,
  "openDept" : "실용외국어(필수)(서울)",
  "openCampus" : "Seoul",
  "area" : "실용외국어(필수)",
  "suggestedYear" : 1,
  "courseNumber" : "U71101203",
  "subjectName" : "실용영어1 (Practical English 1)",
  "professorNameMain" : "윤채영",
  "professorNameAdditional" : "Yoon, Chae-Young",
  "creditHour" : 2,
  "classHour" : 3,
  "time" : [ {
    "dow" : "Mon",
    "time" : [ 4, 5, 6 ],
    "room" : "2204"
  }, {
    "dow" : "Tue",
    "time" : [ 4, 5, 6 ],
    "room" : "2204"
  }, {
    "dow" : "Wed",
    "time" : [ 4, 5, 6 ],
    "room" : "2204"
  }, {
    "dow" : "Thu",
    "time" : [ 4, 5, 6 ],
    "room" : "2204"
  }, {
    "dow" : "Fri",
    "time" : [ 4, 5, 6 ],
    "room" : "2204"
  }, {
    "dow" : "Sat",
    "time" : [ 4, 5, 6 ],
    "room" : "2204"
  } ],
  "applyNo" : 0,
  "maxNo" : 27,
  "note" : "",
  "required" : false,
  "online" : false,
  "foreignLanguage" : false,
  "teamTeaching" : false
}, {
  "openYear" : 2006,
  "openSemester" : 2,
  "openDept" : "실용외국어(필수)(서울)",
  "openCampus" : "Seoul",
  "area" : "실용외국어(필수)",
  "suggestedYear" : 1,
  "courseNumber" : "U71102201",
  "subjectName" : "실용영어2 (Practical English 2)",
  "professorNameMain" : "이현숙(PE)",
  "professorNameAdditional" : "Lee, Hyun Sook",
  "creditHour" : 2,
  "classHour" : 3,
  "time" : [ {
    "dow" : "Mon",
    "time" : [ 1, 2, 3 ],
    "room" : "2402"
  }, {
    "dow" : "Tue",
    "time" : [ 1, 2, 3 ],
    "room" : "2402"
  }, {
    "dow" : "Wed",
    "time" : [ 1, 2, 3 ],
    "room" : "2402"
  }, {
    "dow" : "Thu",
    "time" : [ 1, 2, 3 ],
    "room" : "2402"
  }, {
    "dow" : "Fri",
    "time" : [ 1, 2, 3 ],
    "room" : "2402"
  }, {
    "dow" : "Sat",
    "time" : [ 1, 2, 3 ],
    "room" : "2402"
  } ],
  "applyNo" : 0,
  "maxNo" : 27,
  "note" : "",
  "required" : false,
  "online" : false,
  "foreignLanguage" : false,
  "teamTeaching" : false
}, {
  "openYear" : 2006,
  "openSemester" : 2,
  "openDept" : "실용외국어(필수)(서울)",
  "openCampus" : "Seoul",
  "area" : "실용외국어(필수)",
  "suggestedYear" : 1,
  "courseNumber" : "U71102202",
  "subjectName" : "실용영어2 (Practical English 2)",
  "professorNameMain" : "유세영(E)",
  "professorNameAdditional" : "",
  "creditHour" : 2,
  "classHour" : 3,
  "time" : [ {
    "dow" : "Mon",
    "time" : [ 4, 5, 6 ],
    "room" : "2401"
  }, {
    "dow" : "Tue",
    "time" : [ 4, 5, 6 ],
    "room" : "2401"
  }, {
    "dow" : "Wed",
    "time" : [ 4, 5, 6 ],
    "room" : "2401"
  }, {
    "dow" : "Thu",
    "time" : [ 4, 5, 6 ],
    "room" : "2401"
  }, {
    "dow" : "Fri",
    "time" : [ 4, 5, 6 ],
    "room" : "2401"
  }, {
    "dow" : "Sat",
    "time" : [ 4, 5, 6 ],
    "room" : "2401"
  } ],
  "applyNo" : 0,
  "maxNo" : 27,
  "note" : "",
  "required" : false,
  "online" : false,
  "foreignLanguage" : false,
  "teamTeaching" : false
}, {
  "openYear" : 2006,
  "openSemester" : 2,
  "openDept" : "실용외국어(필수)(서울)",
  "openCampus" : "Seoul",
  "area" : "실용외국어(필수)",
  "suggestedYear" : 1,
  "courseNumber" : "U71102203",
  "subjectName" : "실용영어2 (Practical English 2)",
  "professorNameMain" : "윤영옥",
  "professorNameAdditional" : "Young-Ok Yun",
  "creditHour" : 2,
  "classHour" : 3,
  "time" : [ {
    "dow" : "Mon",
    "time" : [ 4, 5, 6 ],
    "room" : "2402"
  }, {
    "dow" : "Tue",
    "time" : [ 4, 5, 6 ],
    "room" : "2402"
  }, {
    "dow" : "Wed",
    "time" : [ 4, 5, 6 ],
    "room" : "2402"
  }, {
    "dow" : "Thu",
    "time" : [ 4, 5, 6 ],
    "room" : "2402"
  }, {
    "dow" : "Fri",
    "time" : [ 4, 5, 6 ],
    "room" : "2402"
  }, {
    "dow" : "Sat",
    "time" : [ 4, 5, 6 ],
    "room" : "2402"
  } ],
  "applyNo" : 0,
  "maxNo" : 27,
  "note" : "",
  "required" : false,
  "online" : false,
  "foreignLanguage" : false,
  "teamTeaching" : false
}, {
  "openYear" : 2006,
  "openSemester" : 2,
  "openDept" : "실용외국어(필수)(서울)",
  "openCampus" : "Seoul",
  "area" : "실용외국어(필수)",
  "suggestedYear" : 1,
  "courseNumber" : "U71171101",
  "subjectName" : "실용일본어1 (Practical Japanese 1)",
  "professorNameMain" : "신현태",
  "professorNameAdditional" : "",
  "creditHour" : 2,
  "classHour" : 3,
  "time" : [ {
    "dow" : "Mon",
    "time" : [ 1, 2, 3 ],
    "room" : "2404"
  }, {
    "dow" : "Tue",
    "time" : [ 1, 2, 3 ],
    "room" : "2404"
  }, {
    "dow" : "Wed",
    "time" : [ 1, 2, 3 ],
    "room" : "2404"
  }, {
    "dow" : "Thu",
    "time" : [ 1, 2, 3 ],
    "room" : "2404"
  }, {
    "dow" : "Fri",
    "time" : [ 1, 2, 3 ],
    "room" : "2404"
  }, {
    "dow" : "Sat",
    "time" : [ 1, 2, 3 ],
    "room" : "2404"
  } ],
  "applyNo" : 0,
  "maxNo" : 27,
  "note" : "",
  "required" : false,
  "online" : false,
  "foreignLanguage" : false,
  "teamTeaching" : false
}, {
  "openYear" : 2006,
  "openSemester" : 2,
  "openDept" : "실용외국어(필수)(서울)",
  "openCampus" : "Seoul",
  "area" : "실용외국어(필수)",
  "suggestedYear" : 1,
  "courseNumber" : "U71171102",
  "subjectName" : "실용일본어1 (Practical Japanese 1)",
  "professorNameMain" : "신현태",
  "professorNameAdditional" : "",
  "creditHour" : 2,
  "classHour" : 3,
  "time" : [ {
    "dow" : "Mon",
    "time" : [ 4, 5, 6 ],
    "room" : "2404"
  }, {
    "dow" : "Tue",
    "time" : [ 4, 5, 6 ],
    "room" : "2404"
  }, {
    "dow" : "Wed",
    "time" : [ 4, 5, 6 ],
    "room" : "2404"
  }, {
    "dow" : "Thu",
    "time" : [ 4, 5, 6 ],
    "room" : "2404"
  }, {
    "dow" : "Fri",
    "time" : [ 4, 5, 6 ],
    "room" : "2404"
  }, {
    "dow" : "Sat",
    "time" : [ 4, 5, 6 ],
    "room" : "2404"
  } ],
  "applyNo" : 0,
  "maxNo" : 27,
  "note" : "",
  "required" : false,
  "online" : false,
  "foreignLanguage" : false,
  "teamTeaching" : false
}, {
  "openYear" : 2006,
  "openSemester" : 2,
  "openDept" : "실용외국어(필수)(서울)",
  "openCampus" : "Seoul",
  "area" : "실용외국어(필수)",
  "suggestedYear" : 2,
  "courseNumber" : "U71103101",
  "subjectName" : "실용영어3 (Practical English 3)",
  "professorNameMain" : "Chris Kobylinski",
  "professorNameAdditional" : "",
  "creditHour" : 2,
  "classHour" : 3,
  "time" : [ {
    "dow" : "Mon",
    "time" : [ 1, 2, 3 ],
    "room" : "2205"
  }, {
    "dow" : "Tue",
    "time" : [ 1, 2, 3 ],
    "room" : "2205"
  }, {
    "dow" : "Wed",
    "time" : [ 1, 2, 3 ],
    "room" : "2205"
  }, {
    "dow" : "Thu",
    "time" : [ 1, 2, 3 ],
    "room" : "2205"
  }, {
    "dow" : "Fri",
    "time" : [ 1, 2, 3 ],
    "room" : "2205"
  }, {
    "dow" : "Sat",
    "time" : [ 1, 2, 3 ],
    "room" : "2205"
  } ],
  "applyNo" : 0,
  "maxNo" : 30,
  "note" : "",
  "required" : false,
  "online" : false,
  "foreignLanguage" : false,
  "teamTeaching" : false
}, {
  "openYear" : 2006,
  "openSemester" : 2,
  "openDept" : "실용외국어(필수)(서울)",
  "openCampus" : "Seoul",
  "area" : "실용외국어(필수)",
  "suggestedYear" : 2,
  "courseNumber" : "U71103102",
  "subjectName" : "실용영어3 (Practical English 3)",
  "professorNameMain" : "Dean Dawson",
  "professorNameAdditional" : "Dean Dawson ",
  "creditHour" : 2,
  "classHour" : 3,
  "time" : [ {
    "dow" : "Mon",
    "time" : [ 1, 2, 3 ],
    "room" : "2207"
  }, {
    "dow" : "Tue",
    "time" : [ 1, 2, 3 ],
    "room" : "2207"
  }, {
    "dow" : "Wed",
    "time" : [ 1, 2, 3 ],
    "room" : "2207"
  }, {
    "dow" : "Thu",
    "time" : [ 1, 2, 3 ],
    "room" : "2207"
  }, {
    "dow" : "Fri",
    "time" : [ 1, 2, 3 ],
    "room" : "2207"
  }, {
    "dow" : "Sat",
    "time" : [ 1, 2, 3 ],
    "room" : "2207"
  } ],
  "applyNo" : 0,
  "maxNo" : 30,
  "note" : "",
  "required" : false,
  "online" : false,
  "foreignLanguage" : false,
  "teamTeaching" : false
}, {
  "openYear" : 2006,
  "openSemester" : 2,
  "openDept" : "실용외국어(필수)(서울)",
  "openCampus" : "Seoul",
  "area" : "실용외국어(필수)",
  "suggestedYear" : 2,
  "courseNumber" : "U71103103",
  "subjectName" : "실용영어3 (Practical English 3)",
  "professorNameMain" : "Dean Dawson",
  "professorNameAdditional" : "Dean Dawson ",
  "creditHour" : 2,
  "classHour" : 3,
  "time" : [ {
    "dow" : "Mon",
    "time" : [ 4, 5, 6 ],
    "room" : "2205"
  }, {
    "dow" : "Tue",
    "time" : [ 4, 5, 6 ],
    "room" : "2205"
  }, {
    "dow" : "Wed",
    "time" : [ 4, 5, 6 ],
    "room" : "2205"
  }, {
    "dow" : "Thu",
    "time" : [ 4, 5, 6 ],
    "room" : "2205"
  }, {
    "dow" : "Fri",
    "time" : [ 4, 5, 6 ],
    "room" : "2205"
  }, {
    "dow" : "Sat",
    "time" : [ 4, 5, 6 ],
    "room" : "2205"
  } ],
  "applyNo" : 0,
  "maxNo" : 30,
  "note" : "",
  "required" : false,
  "online" : false,
  "foreignLanguage" : false,
  "teamTeaching" : false
}, {
  "openYear" : 2006,
  "openSemester" : 2,
  "openDept" : "실용외국어(필수)(서울)",
  "openCampus" : "Seoul",
  "area" : "실용외국어(필수)",
  "suggestedYear" : 2,
  "courseNumber" : "U71103104",
  "subjectName" : "실용영어3 (Practical English 3)",
  "professorNameMain" : "차영관",
  "professorNameAdditional" : "Cha Young-Kwan",
  "creditHour" : 2,
  "classHour" : 3,
  "time" : [ {
    "dow" : "Mon",
    "time" : [ 1, 2, 3 ],
    "room" : "2209"
  }, {
    "dow" : "Tue",
    "time" : [ 1, 2, 3 ],
    "room" : "2209"
  }, {
    "dow" : "Wed",
    "time" : [ 1, 2, 3 ],
    "room" : "2209"
  }, {
    "dow" : "Thu",
    "time" : [ 1, 2, 3 ],
    "room" : "2209"
  }, {
    "dow" : "Fri",
    "time" : [ 1, 2, 3 ],
    "room" : "2209"
  }, {
    "dow" : "Sat",
    "time" : [ 1, 2, 3 ],
    "room" : "2209"
  } ],
  "applyNo" : 0,
  "maxNo" : 30,
  "note" : "",
  "required" : false,
  "online" : false,
  "foreignLanguage" : false,
  "teamTeaching" : false
}, {
  "openYear" : 2006,
  "openSemester" : 2,
  "openDept" : "실용외국어(필수)(서울)",
  "openCampus" : "Seoul",
  "area" : "실용외국어(필수)",
  "suggestedYear" : 2,
  "courseNumber" : "U71103105",
  "subjectName" : "실용영어3 (Practical English 3)",
  "professorNameMain" : "김재수",
  "professorNameAdditional" : "KIm, Jaesoo",
  "creditHour" : 2,
  "classHour" : 3,
  "time" : [ {
    "dow" : "Mon",
    "time" : [ 4, 5, 6 ],
    "room" : "2209"
  }, {
    "dow" : "Tue",
    "time" : [ 4, 5, 6 ],
    "room" : "2209"
  }, {
    "dow" : "Wed",
    "time" : [ 4, 5, 6 ],
    "room" : "2209"
  }, {
    "dow" : "Thu",
    "time" : [ 4, 5, 6 ],
    "room" : "2209"
  }, {
    "dow" : "Fri",
    "time" : [ 4, 5, 6 ],
    "room" : "2209"
  }, {
    "dow" : "Sat",
    "time" : [ 4, 5, 6 ],
    "room" : "2209"
  } ],
  "applyNo" : 0,
  "maxNo" : 30,
  "note" : "",
  "required" : false,
  "online" : false,
  "foreignLanguage" : false,
  "teamTeaching" : false
}, {
  "openYear" : 2006,
  "openSemester" : 2,
  "openDept" : "실용외국어(필수)(서울)",
  "openCampus" : "Seoul",
  "area" : "실용외국어(필수)",
  "suggestedYear" : 2,
  "courseNumber" : "U71104201",
  "subjectName" : "실용영어4 (Practical English 4)",
  "professorNameMain" : "Shaun Justin Manning",
  "professorNameAdditional" : "",
  "creditHour" : 2,
  "classHour" : 3,
  "time" : [ {
    "dow" : "Mon",
    "time" : [ 1, 2, 3 ],
    "room" : "2208"
  }, {
    "dow" : "Tue",
    "time" : [ 1, 2, 3 ],
    "room" : "2208"
  }, {
    "dow" : "Wed",
    "time" : [ 1, 2, 3 ],
    "room" : "2208"
  }, {
    "dow" : "Thu",
    "time" : [ 1, 2, 3 ],
    "room" : "2208"
  }, {
    "dow" : "Fri",
    "time" : [ 1, 2, 3 ],
    "room" : "2208"
  }, {
    "dow" : "Sat",
    "time" : [ 1, 2, 3 ],
    "room" : "2208"
  } ],
  "applyNo" : 0,
  "maxNo" : 30,
  "note" : "",
  "required" : false,
  "online" : false,
  "foreignLanguage" : false,
  "teamTeaching" : false
}, {
  "openYear" : 2006,
  "openSemester" : 2,
  "openDept" : "실용외국어(필수)(서울)",
  "openCampus" : "Seoul",
  "area" : "실용외국어(필수)",
  "suggestedYear" : 2,
  "courseNumber" : "U71104202",
  "subjectName" : "실용영어4 (Practical English 4)",
  "professorNameMain" : "권정기",
  "professorNameAdditional" : "",
  "creditHour" : 2,
  "classHour" : 3,
  "time" : [ {
    "dow" : "Mon",
    "time" : [ 4, 5, 6 ],
    "room" : "2207"
  }, {
    "dow" : "Tue",
    "time" : [ 4, 5, 6 ],
    "room" : "2207"
  }, {
    "dow" : "Wed",
    "time" : [ 4, 5, 6 ],
    "room" : "2207"
  }, {
    "dow" : "Thu",
    "time" : [ 4, 5, 6 ],
    "room" : "2207"
  }, {
    "dow" : "Fri",
    "time" : [ 4, 5, 6 ],
    "room" : "2207"
  }, {
    "dow" : "Sat",
    "time" : [ 4, 5, 6 ],
    "room" : "2207"
  } ],
  "applyNo" : 0,
  "maxNo" : 30,
  "note" : "",
  "required" : false,
  "online" : false,
  "foreignLanguage" : false,
  "teamTeaching" : false
}, {
  "openYear" : 2006,
  "openSemester" : 2,
  "openDept" : "실용외국어(필수)(서울)",
  "openCampus" : "Seoul",
  "area" : "실용외국어(필수)",
  "suggestedYear" : 2,
  "courseNumber" : "U71104203",
  "subjectName" : "실용영어4 (Practical English 4)",
  "professorNameMain" : "민병숙",
  "professorNameAdditional" : "Min, Byung Sook",
  "creditHour" : 2,
  "classHour" : 3,
  "time" : [ {
    "dow" : "Mon",
    "time" : [ 4, 5, 6 ],
    "room" : "2208"
  }, {
    "dow" : "Tue",
    "time" : [ 4, 5, 6 ],
    "room" : "2208"
  }, {
    "dow" : "Wed",
    "time" : [ 4, 5, 6 ],
    "room" : "2208"
  }, {
    "dow" : "Thu",
    "time" : [ 4, 5, 6 ],
    "room" : "2208"
  }, {
    "dow" : "Fri",
    "time" : [ 4, 5, 6 ],
    "room" : "2208"
  }, {
    "dow" : "Sat",
    "time" : [ 4, 5, 6 ],
    "room" : "2208"
  } ],
  "applyNo" : 0,
  "maxNo" : 30,
  "note" : "",
  "required" : false,
  "online" : false,
  "foreignLanguage" : false,
  "teamTeaching" : false
}, {
  "openYear" : 2006,
  "openSemester" : 2,
  "openDept" : "실용외국어(필수)(서울)",
  "openCampus" : "Seoul",
  "area" : "실용외국어(필수)",
  "suggestedYear" : 2,
  "courseNumber" : "U71104204",
  "subjectName" : "실용영어4 (Practical English 4)",
  "professorNameMain" : "이미라",
  "professorNameAdditional" : "Lee, Mi-Ra",
  "creditHour" : 2,
  "classHour" : 3,
  "time" : [ {
    "dow" : "Mon",
    "time" : [ 1, 2, 3 ],
    "room" : "2408"
  }, {
    "dow" : "Tue",
    "time" : [ 1, 2, 3 ],
    "room" : "2408"
  }, {
    "dow" : "Wed",
    "time" : [ 1, 2, 3 ],
    "room" : "2408"
  }, {
    "dow" : "Thu",
    "time" : [ 1, 2, 3 ],
    "room" : "2408"
  }, {
    "dow" : "Fri",
    "time" : [ 1, 2, 3 ],
    "room" : "2408"
  }, {
    "dow" : "Sat",
    "time" : [ 1, 2, 3 ],
    "room" : "2408"
  } ],
  "applyNo" : 0,
  "maxNo" : 30,
  "note" : "강변",
  "required" : false,
  "online" : false,
  "foreignLanguage" : false,
  "teamTeaching" : false
}, {
  "openYear" : 2006,
  "openSemester" : 2,
  "openDept" : "실용외국어(필수)(서울)",
  "openCampus" : "Seoul",
  "area" : "실용외국어(필수)",
  "suggestedYear" : 2,
  "courseNumber" : "U71104205",
  "subjectName" : "실용영어4 (Practical English 4)",
  "professorNameMain" : "김미혜(실외)",
  "professorNameAdditional" : "Kim Mihye",
  "creditHour" : 2,
  "classHour" : 3,
  "time" : [ {
    "dow" : "Mon",
    "time" : [ 4, 5, 6 ],
    "room" : "2210"
  }, {
    "dow" : "Tue",
    "time" : [ 4, 5, 6 ],
    "room" : "2210"
  }, {
    "dow" : "Wed",
    "time" : [ 4, 5, 6 ],
    "room" : "2210"
  }, {
    "dow" : "Thu",
    "time" : [ 4, 5, 6 ],
    "room" : "2210"
  }, {
    "dow" : "Fri",
    "time" : [ 4, 5, 6 ],
    "room" : "2210"
  }, {
    "dow" : "Sat",
    "time" : [ 4, 5, 6 ],
    "room" : "2210"
  } ],
  "applyNo" : 0,
  "maxNo" : 30,
  "note" : "",
  "required" : false,
  "online" : false,
  "foreignLanguage" : false,
  "teamTeaching" : false
}, {
  "openYear" : 2006,
  "openSemester" : 2,
  "openDept" : "실용외국어(필수)(서울)",
  "openCampus" : "Seoul",
  "area" : "실용외국어(필수)",
  "suggestedYear" : 2,
  "courseNumber" : "U71173101",
  "subjectName" : "실용일본어3 (Practical Japanese 3)",
  "professorNameMain" : "이경화",
  "professorNameAdditional" : "leekyunghwa",
  "creditHour" : 2,
  "classHour" : 3,
  "time" : [ {
    "dow" : "Mon",
    "time" : [ 1, 2, 3 ],
    "room" : "2403"
  }, {
    "dow" : "Tue",
    "time" : [ 1, 2, 3 ],
    "room" : "2403"
  }, {
    "dow" : "Wed",
    "time" : [ 1, 2, 3 ],
    "room" : "2403"
  }, {
    "dow" : "Thu",
    "time" : [ 1, 2, 3 ],
    "room" : "2403"
  }, {
    "dow" : "Fri",
    "time" : [ 1, 2, 3 ],
    "room" : "2403"
  }, {
    "dow" : "Sat",
    "time" : [ 1, 2, 3 ],
    "room" : "2403"
  } ],
  "applyNo" : 0,
  "maxNo" : 27,
  "note" : "",
  "required" : false,
  "online" : false,
  "foreignLanguage" : false,
  "teamTeaching" : false
}, {
  "openYear" : 2006,
  "openSemester" : 2,
  "openDept" : "실용외국어(필수)(서울)",
  "openCampus" : "Seoul",
  "area" : "실용외국어(필수)",
  "suggestedYear" : 2,
  "courseNumber" : "U71173102",
  "subjectName" : "실용일본어3 (Practical Japanese 3)",
  "professorNameMain" : "이경화",
  "professorNameAdditional" : "leekyunghwa",
  "creditHour" : 2,
  "classHour" : 3,
  "time" : [ {
    "dow" : "Mon",
    "time" : [ 4, 5, 6 ],
    "room" : "2403"
  }, {
    "dow" : "Tue",
    "time" : [ 4, 5, 6 ],
    "room" : "2403"
  }, {
    "dow" : "Wed",
    "time" : [ 4, 5, 6 ],
    "room" : "2403"
  }, {
    "dow" : "Thu",
    "time" : [ 4, 5, 6 ],
    "room" : "2403"
  }, {
    "dow" : "Fri",
    "time" : [ 4, 5, 6 ],
    "room" : "2403"
  }, {
    "dow" : "Sat",
    "time" : [ 4, 5, 6 ],
    "room" : "2403"
  } ],
  "applyNo" : 0,
  "maxNo" : 27,
  "note" : "",
  "required" : false,
  "online" : false,
  "foreignLanguage" : false,
  "teamTeaching" : false
} ]