[ {
  "openYear" : 2009,
  "openSemester" : 2,
  "openDept" : "건강과레포츠(서울)",
  "openCampus" : "Seoul",
  "area" : "건강과레포츠",
  "courseNumber" : "U72191101",
  "subjectName" : "다이어트와건강관리 (Healthy Weight Care )",
  "professorNameMain" : "이재문",
  "professorNameAdditional" : "Lee, Jae Moon",
  "creditHour" : 2,
  "classHour" : 2,
  "time" : [ {
    "dow" : "Mon",
    "time" : [ 1, 2 ],
    "room" : "1207"
  }, {
    "dow" : "Tue",
    "time" : [ 1, 2 ],
    "room" : "1207"
  }, {
    "dow" : "Wed",
    "time" : [ 1, 2 ],
    "room" : "1207"
  }, {
    "dow" : "Thu",
    "time" : [ 1, 2 ],
    "room" : "1207"
  }, {
    "dow" : "Fri",
    "time" : [ 1, 2 ],
    "room" : "1207"
  } ],
  "applyNo" : 0,
  "maxNo" : 50,
  "note" : "",
  "required" : false,
  "online" : false,
  "foreignLanguage" : false,
  "teamTeaching" : false
}, {
  "openYear" : 2009,
  "openSemester" : 2,
  "openDept" : "건강과레포츠(서울)",
  "openCampus" : "Seoul",
  "area" : "건강과레포츠",
  "courseNumber" : "U76309101",
  "subjectName" : "여가문화와생활 (The Culture of Leisure & Living)",
  "professorNameMain" : "이재선",
  "professorNameAdditional" : "",
  "creditHour" : 2,
  "classHour" : 2,
  "time" : [ {
    "dow" : "Mon",
    "time" : [ 3, 4 ],
    "room" : "1302"
  }, {
    "dow" : "Tue",
    "time" : [ 3, 4 ],
    "room" : "1302"
  }, {
    "dow" : "Wed",
    "time" : [ 3, 4 ],
    "room" : "1302"
  }, {
    "dow" : "Thu",
    "time" : [ 3, 4 ],
    "room" : "1302"
  }, {
    "dow" : "Fri",
    "time" : [ 3, 4 ],
    "room" : "1302"
  } ],
  "applyNo" : 0,
  "maxNo" : 50,
  "note" : "",
  "required" : false,
  "online" : false,
  "foreignLanguage" : false,
  "teamTeaching" : false
}, {
  "openYear" : 2009,
  "openSemester" : 2,
  "openDept" : "건강과레포츠(서울)",
  "openCampus" : "Seoul",
  "area" : "건강과레포츠",
  "courseNumber" : "U76310101",
  "subjectName" : "운동과체형관리 (Exercise & Weight Control)",
  "professorNameMain" : "김재등",
  "professorNameAdditional" : "Kim JaeDeung",
  "creditHour" : 2,
  "classHour" : 2,
  "time" : [ {
    "dow" : "Mon",
    "time" : [ 5, 6 ],
    "room" : "1304"
  }, {
    "dow" : "Tue",
    "time" : [ 5, 6 ],
    "room" : "1304"
  }, {
    "dow" : "Wed",
    "time" : [ 5, 6 ],
    "room" : "1304"
  }, {
    "dow" : "Thu",
    "time" : [ 5, 6 ],
    "room" : "1304"
  }, {
    "dow" : "Fri",
    "time" : [ 5, 6 ],
    "room" : "1304"
  } ],
  "applyNo" : 0,
  "maxNo" : 50,
  "note" : "",
  "required" : false,
  "online" : false,
  "foreignLanguage" : false,
  "teamTeaching" : false
}, {
  "openYear" : 2009,
  "openSemester" : 2,
  "openDept" : "건강과레포츠(서울)",
  "openCampus" : "Seoul",
  "area" : "건강과레포츠",
  "courseNumber" : "U51523301",
  "subjectName" : "체육(댄스스포츠) (Physical Education (Dance Sports))",
  "professorNameMain" : "이재희",
  "professorNameAdditional" : "Lee Jae Hee",
  "creditHour" : 1,
  "classHour" : 2,
  "time" : [ {
    "dow" : "Mon",
    "time" : [ 7, 8 ],
    "room" : "0206-2"
  }, {
    "dow" : "Tue",
    "time" : [ 7, 8 ],
    "room" : "0206-2"
  }, {
    "dow" : "Wed",
    "time" : [ 7, 8 ],
    "room" : "0206-2"
  }, {
    "dow" : "Thu",
    "time" : [ 7, 8 ],
    "room" : "0206-2"
  }, {
    "dow" : "Fri",
    "time" : [ 7, 8 ],
    "room" : "0206-2"
  } ],
  "applyNo" : 0,
  "maxNo" : 30,
  "note" : "",
  "required" : false,
  "online" : false,
  "foreignLanguage" : false,
  "teamTeaching" : false
}, {
  "openYear" : 2009,
  "openSemester" : 2,
  "openDept" : "건강과레포츠(서울)",
  "openCampus" : "Seoul",
  "area" : "건강과레포츠",
  "courseNumber" : "U76119301",
  "subjectName" : "체육(볼링) (Physical Education (Bowling))",
  "professorNameMain" : "이재영",
  "professorNameAdditional" : "Lee, Jae Young",
  "creditHour" : 1,
  "classHour" : 2,
  "time" : [ {
    "dow" : "Mon",
    "time" : [ 1, 2 ],
    "room" : "1304"
  }, {
    "dow" : "Tue",
    "time" : [ 1, 2 ],
    "room" : "1304"
  }, {
    "dow" : "Wed",
    "time" : [ 1, 2 ],
    "room" : "1304"
  }, {
    "dow" : "Thu",
    "time" : [ 1, 2 ],
    "room" : "1304"
  }, {
    "dow" : "Fri",
    "time" : [ 1, 2 ],
    "room" : "1304"
  } ],
  "applyNo" : 0,
  "maxNo" : 30,
  "note" : "별도의 실습비가 추가될 예정임(50,000원)",
  "required" : false,
  "online" : false,
  "foreignLanguage" : false,
  "teamTeaching" : false
}, {
  "openYear" : 2009,
  "openSemester" : 2,
  "openDept" : "건강과레포츠(서울)",
  "openCampus" : "Seoul",
  "area" : "건강과레포츠",
  "courseNumber" : "U76106101",
  "subjectName" : "체육(요가) (Physical Education (Yoga))",
  "professorNameMain" : "김연숙",
  "professorNameAdditional" : "Kim Yeon-suk",
  "creditHour" : 1,
  "classHour" : 2,
  "time" : [ {
    "dow" : "Mon",
    "time" : [ 7, 8 ],
    "room" : "5003"
  }, {
    "dow" : "Tue",
    "time" : [ 7, 8 ],
    "room" : "5003"
  }, {
    "dow" : "Wed",
    "time" : [ 7, 8 ],
    "room" : "5003"
  }, {
    "dow" : "Thu",
    "time" : [ 7, 8 ],
    "room" : "5003"
  }, {
    "dow" : "Fri",
    "time" : [ 7, 8 ],
    "room" : "5003"
  } ],
  "applyNo" : 0,
  "maxNo" : 25,
  "note" : "",
  "required" : false,
  "online" : false,
  "foreignLanguage" : false,
  "teamTeaching" : false
} ]