[ {
  "openYear" : 2011,
  "openSemester" : 4,
  "openDept" : "실용외국어(선택)(서울)",
  "openCampus" : "Seoul",
  "area" : "실용외국어(선택)",
  "suggestedYear" : 2,
  "courseNumber" : "U71194101",
  "subjectName" : "관광일본어2 (Travel Japanese 2)",
  "professorNameMain" : "김정헌",
  "professorNameAdditional" : "Kim jeong heon",
  "creditHour" : 2,
  "classHour" : 2,
  "time" : [ {
    "dow" : "Mon",
    "time" : [ 3, 4 ],
    "room" : "2201"
  }, {
    "dow" : "Tue",
    "time" : [ 3, 4 ],
    "room" : "2201"
  }, {
    "dow" : "Wed",
    "time" : [ 3, 4 ],
    "room" : "2201"
  }, {
    "dow" : "Thu",
    "time" : [ 3, 4 ],
    "room" : "2201"
  }, {
    "dow" : "Fri",
    "time" : [ 3, 4 ],
    "room" : "2201"
  } ],
  "applyNo" : 0,
  "maxNo" : 35,
  "note" : "",
  "required" : false,
  "online" : false,
  "foreignLanguage" : false,
  "teamTeaching" : false
}, {
  "openYear" : 2011,
  "openSemester" : 4,
  "openDept" : "실용외국어(선택)(서울)",
  "openCampus" : "Seoul",
  "area" : "실용외국어(선택)",
  "suggestedYear" : 2,
  "courseNumber" : "E01103301",
  "subjectName" : "실용영문법(실외) (Practical English Grammar )",
  "professorNameMain" : "사재진",
  "professorNameAdditional" : "Sa Jae Jin",
  "creditHour" : 2,
  "classHour" : 2,
  "time" : [ {
    "dow" : "Mon",
    "time" : [ 3, 4 ],
    "room" : "2210"
  }, {
    "dow" : "Tue",
    "time" : [ 3, 4 ],
    "room" : "2210"
  }, {
    "dow" : "Wed",
    "time" : [ 3, 4 ],
    "room" : "2210"
  }, {
    "dow" : "Thu",
    "time" : [ 3, 4 ],
    "room" : "2210"
  }, {
    "dow" : "Fri",
    "time" : [ 3, 4 ],
    "room" : "2210"
  } ],
  "applyNo" : 0,
  "maxNo" : 35,
  "note" : "",
  "required" : false,
  "online" : false,
  "foreignLanguage" : false,
  "teamTeaching" : false
}, {
  "openYear" : 2011,
  "openSemester" : 4,
  "openDept" : "실용외국어(선택)(서울)",
  "openCampus" : "Seoul",
  "area" : "실용외국어(선택)",
  "suggestedYear" : 2,
  "courseNumber" : "E01103302",
  "subjectName" : "실용영문법(실외) (Practical English Grammar )",
  "professorNameMain" : "사재진",
  "professorNameAdditional" : "Sa Jae Jin",
  "creditHour" : 2,
  "classHour" : 2,
  "time" : [ {
    "dow" : "Mon",
    "time" : [ 5, 6 ],
    "room" : "2210"
  }, {
    "dow" : "Tue",
    "time" : [ 5, 6 ],
    "room" : "2210"
  }, {
    "dow" : "Wed",
    "time" : [ 5, 6 ],
    "room" : "2210"
  }, {
    "dow" : "Thu",
    "time" : [ 5, 6 ],
    "room" : "2210"
  }, {
    "dow" : "Fri",
    "time" : [ 5, 6 ],
    "room" : "2210"
  } ],
  "applyNo" : 0,
  "maxNo" : 35,
  "note" : "",
  "required" : false,
  "online" : false,
  "foreignLanguage" : false,
  "teamTeaching" : false
}, {
  "openYear" : 2011,
  "openSemester" : 4,
  "openDept" : "실용외국어(선택)(서울)",
  "openCampus" : "Seoul",
  "area" : "실용외국어(선택)",
  "suggestedYear" : 2,
  "courseNumber" : "U71264101",
  "subjectName" : "영.미문화영어읽기 (Reading British/American Culture)",
  "professorNameMain" : "오미숙",
  "professorNameAdditional" : "O Mee-Sook",
  "creditHour" : 2,
  "classHour" : 2,
  "time" : [ {
    "dow" : "Mon",
    "time" : [ 1, 2 ],
    "room" : "2204"
  }, {
    "dow" : "Tue",
    "time" : [ 1, 2 ],
    "room" : "2204"
  }, {
    "dow" : "Wed",
    "time" : [ 1, 2 ],
    "room" : "2204"
  }, {
    "dow" : "Thu",
    "time" : [ 1, 2 ],
    "room" : "2204"
  }, {
    "dow" : "Fri",
    "time" : [ 1, 2 ],
    "room" : "2204"
  } ],
  "applyNo" : 0,
  "maxNo" : 35,
  "note" : "",
  "required" : false,
  "online" : false,
  "foreignLanguage" : false,
  "teamTeaching" : false
}, {
  "openYear" : 2011,
  "openSemester" : 4,
  "openDept" : "실용외국어(선택)(서울)",
  "openCampus" : "Seoul",
  "area" : "실용외국어(선택)",
  "suggestedYear" : 2,
  "courseNumber" : "U71264102",
  "subjectName" : "영.미문화영어읽기 (Reading British/American Culture)",
  "professorNameMain" : "오미숙",
  "professorNameAdditional" : "O Mee-Sook",
  "creditHour" : 2,
  "classHour" : 2,
  "time" : [ {
    "dow" : "Mon",
    "time" : [ 3, 4 ],
    "room" : "2204"
  }, {
    "dow" : "Tue",
    "time" : [ 3, 4 ],
    "room" : "2204"
  }, {
    "dow" : "Wed",
    "time" : [ 3, 4 ],
    "room" : "2204"
  }, {
    "dow" : "Thu",
    "time" : [ 3, 4 ],
    "room" : "2204"
  }, {
    "dow" : "Fri",
    "time" : [ 3, 4 ],
    "room" : "2204"
  } ],
  "applyNo" : 0,
  "maxNo" : 35,
  "note" : "",
  "required" : false,
  "online" : false,
  "foreignLanguage" : false,
  "teamTeaching" : false
}, {
  "openYear" : 2011,
  "openSemester" : 4,
  "openDept" : "실용외국어(선택)(서울)",
  "openCampus" : "Seoul",
  "area" : "실용외국어(선택)",
  "suggestedYear" : 2,
  "courseNumber" : "U71266101",
  "subjectName" : "영어베스트셀러읽기 (Reading English Bestseller)",
  "professorNameMain" : "최순근",
  "professorNameAdditional" : "Choi, Sun-Geun",
  "creditHour" : 2,
  "classHour" : 2,
  "time" : [ {
    "dow" : "Mon",
    "time" : [ 1, 2 ],
    "room" : "2209"
  }, {
    "dow" : "Tue",
    "time" : [ 1, 2 ],
    "room" : "2209"
  }, {
    "dow" : "Wed",
    "time" : [ 1, 2 ],
    "room" : "2209"
  }, {
    "dow" : "Thu",
    "time" : [ 1, 2 ],
    "room" : "2209"
  }, {
    "dow" : "Fri",
    "time" : [ 1, 2 ],
    "room" : "2209"
  } ],
  "applyNo" : 0,
  "maxNo" : 35,
  "note" : "",
  "required" : false,
  "online" : false,
  "foreignLanguage" : false,
  "teamTeaching" : false
}, {
  "openYear" : 2011,
  "openSemester" : 4,
  "openDept" : "실용외국어(선택)(서울)",
  "openCampus" : "Seoul",
  "area" : "실용외국어(선택)",
  "suggestedYear" : 2,
  "courseNumber" : "U71266102",
  "subjectName" : "영어베스트셀러읽기 (Reading English Bestseller)",
  "professorNameMain" : "최순근",
  "professorNameAdditional" : "Choi, Sun-Geun",
  "creditHour" : 2,
  "classHour" : 2,
  "time" : [ {
    "dow" : "Mon",
    "time" : [ 3, 4 ],
    "room" : "2209"
  }, {
    "dow" : "Tue",
    "time" : [ 3, 4 ],
    "room" : "2209"
  }, {
    "dow" : "Wed",
    "time" : [ 3, 4 ],
    "room" : "2209"
  }, {
    "dow" : "Thu",
    "time" : [ 3, 4 ],
    "room" : "2209"
  }, {
    "dow" : "Fri",
    "time" : [ 3, 4 ],
    "room" : "2209"
  } ],
  "applyNo" : 0,
  "maxNo" : 35,
  "note" : "",
  "required" : false,
  "online" : false,
  "foreignLanguage" : false,
  "teamTeaching" : false
}, {
  "openYear" : 2011,
  "openSemester" : 4,
  "openDept" : "실용외국어(선택)(서울)",
  "openCampus" : "Seoul",
  "area" : "실용외국어(선택)",
  "suggestedYear" : 3,
  "courseNumber" : "U71271101",
  "subjectName" : "IBT토익(말하기/쓰기) (IBT TOEIC (Speaking/Writing))",
  "professorNameMain" : "오수진",
  "professorNameAdditional" : "Oh Sujin",
  "creditHour" : 2,
  "classHour" : 2,
  "time" : [ {
    "dow" : "Mon",
    "time" : [ 5, 6 ],
    "room" : "2203"
  }, {
    "dow" : "Tue",
    "time" : [ 5, 6 ],
    "room" : "2203"
  }, {
    "dow" : "Wed",
    "time" : [ 5, 6 ],
    "room" : "2203"
  }, {
    "dow" : "Thu",
    "time" : [ 5, 6 ],
    "room" : "2203"
  }, {
    "dow" : "Fri",
    "time" : [ 5, 6 ],
    "room" : "2203"
  } ],
  "applyNo" : 0,
  "maxNo" : 35,
  "note" : "",
  "required" : false,
  "online" : false,
  "foreignLanguage" : false,
  "teamTeaching" : false
} ]