[ {
  "openYear" : 2015,
  "openSemester" : 3,
  "openDept" : "(서울)-철학과(Department of Philosophy)",
  "openCampus" : "Seoul",
  "area" : "부전공",
  "suggestedYear" : 2,
  "courseNumber" : "R04202101",
  "subjectName" : "서양근.현대철학사 (History of Western Modern & Contemporary Philosophy)",
  "professorNameMain" : "이준",
  "professorNameAdditional" : "Lee Joon",
  "creditHour" : 3,
  "classHour" : 3,
  "time" : [ {
    "dow" : "Mon",
    "time" : [ 1, 2, 3 ],
    "room" : "1409"
  } ],
  "applyNo" : 0,
  "maxNo" : 60,
  "note" : "",
  "required" : false,
  "online" : false,
  "foreignLanguage" : false,
  "teamTeaching" : false
}, {
  "openYear" : 2015,
  "openSemester" : 3,
  "openDept" : "(서울)-철학과(Department of Philosophy)",
  "openCampus" : "Seoul",
  "area" : "부전공",
  "suggestedYear" : 2,
  "courseNumber" : "R01102101",
  "subjectName" : "인식론 (Epistemology)",
  "professorNameMain" : "정재환",
  "professorNameAdditional" : "Chung Jaehwan",
  "creditHour" : 3,
  "classHour" : 3,
  "time" : [ {
    "dow" : "Fri",
    "time" : [ 1, 2, 3 ],
    "room" : "3404"
  } ],
  "applyNo" : 0,
  "maxNo" : 60,
  "note" : "",
  "required" : false,
  "online" : false,
  "foreignLanguage" : false,
  "teamTeaching" : false
}, {
  "openYear" : 2015,
  "openSemester" : 3,
  "openDept" : "(서울)-철학과(Department of Philosophy)",
  "openCampus" : "Seoul",
  "area" : "부전공",
  "suggestedYear" : 2,
  "courseNumber" : "R01202101",
  "subjectName" : "한국철학사 (History of Korean Philosophy)",
  "professorNameMain" : "김미림",
  "professorNameAdditional" : "Kim, Mi-Lim",
  "creditHour" : 3,
  "classHour" : 3,
  "time" : [ {
    "dow" : "Fri",
    "time" : [ 7, 8, 9 ],
    "room" : "C309"
  } ],
  "applyNo" : 0,
  "maxNo" : 60,
  "note" : "논술교육인증",
  "required" : false,
  "online" : false,
  "foreignLanguage" : false,
  "teamTeaching" : false
}, {
  "openYear" : 2015,
  "openSemester" : 3,
  "openDept" : "(서울)-철학과(Department of Philosophy)",
  "openCampus" : "Seoul",
  "area" : "부전공",
  "suggestedYear" : 3,
  "courseNumber" : "R01324101",
  "subjectName" : "동서양비교문화론 (Studies of Comparative Culture in Eastern and Western Culture )",
  "professorNameMain" : "소병선",
  "professorNameAdditional" : "So, ByungSeon",
  "creditHour" : 3,
  "classHour" : 3,
  "time" : [ {
    "dow" : "Tue",
    "time" : [ 4, 5, 6 ],
    "room" : "2208"
  } ],
  "applyNo" : 0,
  "maxNo" : 60,
  "note" : "논술교육인증",
  "required" : false,
  "online" : false,
  "foreignLanguage" : false,
  "teamTeaching" : false
}, {
  "openYear" : 2015,
  "openSemester" : 3,
  "openDept" : "(서울)-철학과(Department of Philosophy)",
  "openCampus" : "Seoul",
  "area" : "부전공",
  "suggestedYear" : 3,
  "courseNumber" : "R01360101",
  "subjectName" : "존재론 (Ontology)",
  "professorNameMain" : "구연상",
  "professorNameAdditional" : "Gu, Yeonsang",
  "creditHour" : 3,
  "classHour" : 3,
  "time" : [ {
    "dow" : "Thu",
    "time" : [ 1, 2, 3 ],
    "room" : "C309"
  } ],
  "applyNo" : 0,
  "maxNo" : 60,
  "note" : "",
  "required" : false,
  "online" : false,
  "foreignLanguage" : false,
  "teamTeaching" : false
}, {
  "openYear" : 2015,
  "openSemester" : 3,
  "openDept" : "(서울)-철학과(Department of Philosophy)",
  "openCampus" : "Seoul",
  "area" : "부전공",
  "suggestedYear" : 3,
  "courseNumber" : "V42456101",
  "subjectName" : "프랑스현대철학 (French Contemporary Philosophy)",
  "professorNameMain" : "김윤재",
  "professorNameAdditional" : "Kim Yun Jai",
  "creditHour" : 3,
  "classHour" : 3,
  "time" : [ {
    "dow" : "Thu",
    "time" : [ 4, 5, 6 ],
    "room" : "3502"
  } ],
  "applyNo" : 0,
  "maxNo" : 60,
  "note" : "",
  "required" : false,
  "online" : false,
  "foreignLanguage" : false,
  "teamTeaching" : false
}, {
  "openYear" : 2015,
  "openSemester" : 3,
  "openDept" : "(서울)-철학과(Department of Philosophy)",
  "openCampus" : "Seoul",
  "area" : "부전공",
  "suggestedYear" : 4,
  "courseNumber" : "R01419101",
  "subjectName" : "동양철학고전선독 (Reading on the Selected Classics in Oriental Philosophy)",
  "professorNameMain" : "김원명",
  "professorNameAdditional" : "Kim, Won Myoung",
  "creditHour" : 3,
  "classHour" : 3,
  "time" : [ {
    "dow" : "Mon",
    "time" : [ 4, 5, 6 ],
    "room" : "2402"
  } ],
  "applyNo" : 0,
  "maxNo" : 60,
  "note" : "",
  "required" : false,
  "online" : false,
  "foreignLanguage" : true,
  "teamTeaching" : false
}, {
  "openYear" : 2015,
  "openSemester" : 3,
  "openDept" : "(서울)-철학과(Department of Philosophy)",
  "openCampus" : "Seoul",
  "area" : "부전공",
  "suggestedYear" : 4,
  "courseNumber" : "R01441101",
  "subjectName" : "생명윤리학 (Bioethics)",
  "professorNameMain" : "김신",
  "professorNameAdditional" : "Shin Kim",
  "creditHour" : 3,
  "classHour" : 3,
  "time" : [ {
    "dow" : "Wed",
    "time" : [ 1, 2, 3 ],
    "room" : "2208"
  } ],
  "applyNo" : 0,
  "maxNo" : 60,
  "note" : "논술교육인증",
  "required" : false,
  "online" : false,
  "foreignLanguage" : true,
  "teamTeaching" : false
}, {
  "openYear" : 2015,
  "openSemester" : 3,
  "openDept" : "(서울)-철학과(Department of Philosophy)",
  "openCampus" : "Seoul",
  "area" : "부전공",
  "suggestedYear" : 4,
  "courseNumber" : "R01416101",
  "subjectName" : "포스트모더니즘 (Post-Mordernism )",
  "professorNameMain" : "주성호",
  "professorNameAdditional" : "",
  "creditHour" : 3,
  "classHour" : 3,
  "time" : [ {
    "dow" : "Wed",
    "time" : [ 7, 8, 9 ],
    "room" : "C306"
  } ],
  "applyNo" : 0,
  "maxNo" : 60,
  "note" : "",
  "required" : false,
  "online" : false,
  "foreignLanguage" : false,
  "teamTeaching" : false
} ]